gphotospy/__init__.py
gphotospy/album.py
gphotospy/authorize.py
gphotospy/media.py
gphotospy/sharedalbum.py
gphotospy/upload.py
gphotospy/utils.py
gphotospy-0.2.1.dist-info/LICENSE
gphotospy-0.2.1.dist-info/METADATA
gphotospy-0.2.1.dist-info/WHEEL
gphotospy-0.2.1.dist-info/top_level.txt
gphotospy-0.2.1.dist-info/RECORD
