Metadata-Version: 2.1
Name: gphotospy
Version: 0.2.1
Summary: Unofficial Google Photos Python library
Home-page: https://github.com/davidedelpapa/gphotospy
Author: Davide Del Papa
Author-email: davidedelpapa@gmail.com
License: MIT
Platform: UNKNOWN
Classifier: License :: OSI Approved :: MIT License
Classifier: Programming Language :: Python :: 3
Classifier: Programming Language :: Python :: 3.7
License-File: LICENSE
Requires-Dist: google-api-python-client (>=2.1.0)
Requires-Dist: google-auth-httplib2 (>=0.1.0)
Requires-Dist: google-auth-oauthlib (>=0.4.4)
Requires-Dist: oauth2client (>=4.1.3)
